spec2scl/__init__.py
spec2scl/bin.py
spec2scl/convertor.py
spec2scl/decorators.py
spec2scl/metapackage.py
spec2scl/settings.py
spec2scl/specfile.py
spec2scl/transformer.py
spec2scl/version.py
spec2scl/templates/metapackage.spec
spec2scl/transformers/__init__.py
spec2scl/transformers/generic.py
spec2scl-1.2.2.dist-info/LICENSE
spec2scl-1.2.2.dist-info/METADATA
spec2scl-1.2.2.dist-info/WHEEL
spec2scl-1.2.2.dist-info/entry_points.txt
spec2scl-1.2.2.dist-info/top_level.txt
spec2scl-1.2.2.dist-info/RECORD
