Metadata-Version: 2.1
Name: spec2scl
Version: 1.2.2
Summary: Convert RPM specfiles to SCL-style.
Home-page: https://bitbucket.org/bkabrda/spec2scl/
Author: Slavek Kabrda, Robert Kuska, Iryna Shcherbina
Author-email: slavek@redhat.com, rkuska@redhat.com, ishcherb@redhat.com
Maintainer: Jan Staněk
Maintainer-email: jstanek@redhat.com
License: MIT
Keywords: rpm,spec,specfile,convert,scl,dsc
Platform: UNKNOWN
Classifier: Development Status :: 4 - Beta
Classifier: Environment :: Console
Classifier: Intended Audience :: Developers
Classifier: Intended Audience :: System Administrators
Classifier: License :: OSI Approved :: MIT License
Classifier: Operating System :: POSIX :: Linux
Classifier: Programming Language :: Python
Classifier: Topic :: Software Development :: Build Tools
Classifier: Topic :: System :: Software Distribution
Requires-Dist: jinja2
